toy/__init__.py
toy/solvers.py
toy/utils.py
toy/app/__init__.py
toy/app/app.py
toy/compiler/__init__.py
toy/compiler/base.py
toy/core/__init__.py
toy/core/meta.py
toy/core/model.py
toy/core/model_meta.py
toy/core/run.py
toy/core/value.py
toy/examples/dice.py
toy/examples/lorenz.py
toy/examples/particle.py
toy/examples/population.py
toy/examples/simple.py
toy/types/__init__.py
toy/types/namedarray.py
toy/unit/__init__.py
toy/unit/definitions.py
toy/unit/unit.py
toy_model-0.1.0.dist-info/LICENSE
toy_model-0.1.0.dist-info/WHEEL
toy_model-0.1.0.dist-info/METADATA
toy_model-0.1.0.dist-info/RECORD
